flask_util_js.py
flask_util_js-0.2.26.dist-info/METADATA
flask_util_js-0.2.26.dist-info/WHEEL
flask_util_js-0.2.26.dist-info/top_level.txt
flask_util_js-0.2.26.dist-info/RECORD
