Metadata-Version: 2.1
Name: flask-util-js
Version: 0.2.26
Summary: flask's util in javascript. such as url_for etc.
Home-page: https://github.com/dantezhu/flask_util_js
Author: dantezhu
Author-email: dantezhu <zny2008@gmail.com>
License: BSD
Project-URL: Homepage, https://github.com/dantezhu/flask_util_js
Platform: any
Requires-Dist: flask
